{
  "$schema" : "http://json-schema.org/draft-07/schema#",
  "type" : "object",
  "required" : [ "enabled", "appliedBodyInjectionPathPrefixes" ],
  "properties" : {
    "enabled" : {
      "type" : "boolean",
      "description" : "indicator of enabled",
      "default" : true
    },
    "appliedBodyInjectionPathPrefixes" : {
      "type" : "array",
      "description" : "response body injection applied path prefixes. Injecting the response body and output into the audit log is very heavy operation,\nand it should only be enabled when necessary or for diagnose session to resolve issues. This list can be updated on the config\nserver or local values.yml, then an API call to the config-reload endpoint to apply the changes from light-portal control pane.\nPlease be aware that big response body will only log the beginning part of it in the audit log and gzip encoded response body can\nnot be injected. Even the body injection is not applied, you can still transform the response for headers, query parameters, path\nparameters etc. The format is a list of strings separated with commas or a JSON list in values.yml definition from config server,\nor you can use yaml format in this file or values.yaml on local filesystem. The following are the examples.\nresponse-injection.appliedBodyInjectionPathPrefixes: [\"/v1/cats\", \"/v1/dogs\"]\nresponse-injection.appliedBodyInjectionPathPrefixes: /v1/cats, /v1/dogs\nresponse-injection.appliedBodyInjectionPathPrefixes:\n  - /v1/cats\n  - /v1/dogs",
      "items" : {
        "type" : "string"
      }
    }
  }
}