{
  "id" : "",
  "data" : {
    "configId" : "",
    "updateTs" : "",
    "classPath" : "com.networknt.cache.CacheConfig",
    "configDesc" : null,
    "configName" : "cache",
    "configType" : "Handler",
    "updateUser" : "",
    "configPhase" : ""
  },
  "host" : "",
  "time" : "",
  "type" : "ConfigCreatedEvent",
  "user" : "",
  "nonce" : "",
  "source" : "https://github.com/networknt/light4j",
  "subject" : "",
  "specversion" : "",
  "aggregatetype" : "Config",
  "datacontenttype" : "application/json",
  "aggregateversion" : ""
}